smscallbomber/SMSCallBomber.py
smscallbomber/Services.py
smscallbomber/User_Agent.py
smscallbomber/__init__.py
smscallbomber/config.py
smscallbomber/service.py
smscallbomber-2.7.dist-info/licenses/LICENSE
smscallbomber-2.7.dist-info/METADATA
smscallbomber-2.7.dist-info/WHEEL
smscallbomber-2.7.dist-info/top_level.txt
smscallbomber-2.7.dist-info/RECORD
