Metadata-Version: 2.4
Name: smscallbomber
Version: 2.7
Summary: A library for SMS and call bomber / Библиотека для SMS бомбера со звонками
Home-page: https://github.com/BabayVadimovich/SMSCallBomber
Author: BabayVadimovich
Author-email: hmatvej49@gmail.com
Keywords: bomber,sms,call,smsbomber
Classifier: Programming Language :: Python :: 3
Classifier: License :: OSI Approved :: MIT License
Classifier: Operating System :: OS Independent
License-File: LICENSE
Requires-Dist: asyncio
Requires-Dist: argparse
Requires-Dist: aiohttp
Dynamic: author
Dynamic: author-email
Dynamic: classifier
Dynamic: description
Dynamic: description-content-type
Dynamic: home-page
Dynamic: keywords
Dynamic: license-file
Dynamic: requires-dist
Dynamic: summary
